textapp/__init__.py
textapp/formatting.py
textapp/menu_user.py
textapp/text_app.py
textapp/url_user.py
textapp-0.0.2.dist-info/LICENSE
textapp-0.0.2.dist-info/METADATA
textapp-0.0.2.dist-info/WHEEL
textapp-0.0.2.dist-info/top_level.txt
textapp-0.0.2.dist-info/RECORD
