Metadata-Version: 2.1
Name: textapp
Version: 0.0.2
Summary: Create simple but useful terminal menus.
Home-page: https://github.com/TandonDevOps/textapp
Author: Gene Callahan
Author-email: gcallah@mac.com
License: UNKNOWN
Platform: UNKNOWN
Classifier: Programming Language :: Python :: 3
Classifier: License :: OSI Approved :: GNU General Public License v3 (GPLv3)
Classifier: Operating System :: OS Independent
